{"expires_at": 1776669911.7889285, "value": [{"player_id": "20002003", "game_id": "23616", "team": "CHA", "opponent": "NY", "game_date": "2026-04-12T00:00:00", "home_or_away": "AWAY", "min": 32.0, "pts": 12.2, "reb": 1.7, "ast": 3.5, "stl": 0.0, "blk": 0.0, "tov": 0.0, "fg3m": 0.0, "fga": 10.6, "fgm": 5.2, "fantasy_points": 14.8}, {"player_id": "20002003", "game_id": "23597", "team": "CHA", "opponent": "DET", "game_date": "2026-04-10T00:00:00", "home_or_away": "HOME", "min": 30.0, "pts": 13.2, "reb": 10.6, "ast": 5.2, "stl": 0.0, "blk": 3.5, "tov": 0.0, "fg3m": 1.7, "fga": 12.2, "fgm": 5.2, "fantasy_points": 38.3}, {"player_id": "20002003", "game_id": "23644", "team": "CHA", "opponent": "BOS", "game_date": "2026-04-07T00:00:00", "home_or_away": "AWAY", "min": 41.0, "pts": 17.2, "reb": 15.8, "ast": 7.0, "stl": 0.0, "blk": 0.0, "tov": 1.7, "fg3m": 1.7, "fga": 11.9, "fgm": 8.7, "fantasy_points": 46.9}, {"player_id": "20002003", "game_id": "23632", "team": "CHA", "opponent": "MIN", "game_date": "2026-04-05T00:00:00", "home_or_away": "AWAY", "min": 44.0, "pts": 33.0, "reb": 10.6, "ast": 12.2, "stl": 0.0, "blk": 0.0, "tov": 3.5, "fg3m": 7.0, "fga": 15.8, "fgm": 13.2, "fantasy_points": 61.4}, {"player_id": "20002003", "game_id": "23585", "team": "CHA", "opponent": "IND", "game_date": "2026-04-03T00:00:00", "home_or_away": "HOME", "min": 33.0, "pts": 25.1, "reb": 10.5, "ast": 1.7, "stl": 0.0, "blk": 1.7, "tov": 1.7, "fg3m": 5.2, "fga": 21.1, "fgm": 12.2, "fantasy_points": 40.9}, {"player_id": "20002003", "game_id": "23579", "team": "CHA", "opponent": "PHO", "game_date": "2026-04-02T00:00:00", "home_or_away": "HOME", "min": 34.0, "pts": 33.0, "reb": 7.0, "ast": 3.5, "stl": 1.7, "blk": 0.0, "tov": 3.5, "fg3m": 7.0, "fga": 21.1, "fgm": 13.2, "fantasy_points": 47.5}, {"player_id": "20002003", "game_id": "23565", "team": "CHA", "opponent": "BKN", "game_date": "2026-03-31T00:00:00", "home_or_away": "AWAY", "min": 30.0, "pts": 25.1, "reb": 8.7, "ast": 3.5, "stl": 7.0, "blk": 1.7, "tov": 0.0, "fg3m": 1.7, "fga": 15.8, "fgm": 12.2, "fantasy_points": 51.2}, {"player_id": "20002003", "game_id": "23550", "team": "CHA", "opponent": "BOS", "game_date": "2026-03-29T00:00:00", "home_or_away": "HOME", "min": 38.0, "pts": 18.5, "reb": 3.5, "ast": 3.5, "stl": 0.0, "blk": 0.0, "tov": 1.7, "fg3m": 0.0, "fga": 11.9, "fgm": 8.7, "fantasy_points": 25.1}, {"player_id": "20002003", "game_id": "23542", "team": "CHA", "opponent": "PHI", "game_date": "2026-03-28T00:00:00", "home_or_away": "HOME", "min": 38.0, "pts": 14.5, "reb": 10.5, "ast": 1.7, "stl": 0.0, "blk": 0.0, "tov": 0.0, "fg3m": 1.7, "fga": 11.9, "fgm": 7.0, "fantasy_points": 27.1}, {"player_id": "20002003", "game_id": "23528", "team": "CHA", "opponent": "NY", "game_date": "2026-03-26T00:00:00", "home_or_away": "HOME", "min": 41.0, "pts": 22.4, "reb": 8.7, "ast": 5.2, "stl": 0.0, "blk": 0.0, "tov": 1.7, "fg3m": 0.0, "fga": 22.4, "fgm": 10.6, "fantasy_points": 36.0}, {"player_id": "20002003", "game_id": "23512", "team": "CHA", "opponent": "SAC", "game_date": "2026-03-24T00:00:00", "home_or_away": "HOME", "min": 32.0, "pts": 11.9, "reb": 10.6, "ast": 7.0, "stl": 0.0, "blk": 0.0, "tov": 3.5, "fg3m": 0.0, "fga": 10.6, "fgm": 7.0, "fantasy_points": 31.7}, {"player_id": "20002003", "game_id": "23488", "team": "CHA", "opponent": "MEM", "game_date": "2026-03-21T00:00:00", "home_or_away": "HOME", "min": 34.0, "pts": 17.2, "reb": 7.0, "ast": 1.7, "stl": 1.7, "blk": 0.0, "tov": 1.7, "fg3m": 0.0, "fga": 10.6, "fgm": 10.5, "fantasy_points": 27.7}, {"player_id": "20002003", "game_id": "23473", "team": "CHA", "opponent": "ORL", "game_date": "2026-03-19T00:00:00", "home_or_away": "HOME", "min": 29.0, "pts": 14.5, "reb": 5.2, "ast": 0.0, "stl": 0.0, "blk": 0.0, "tov": 1.7, "fg3m": 1.7, "fga": 10.6, "fgm": 7.0, "fantasy_points": 19.5}, {"player_id": "20002003", "game_id": "23456", "team": "CHA", "opponent": "MIA", "game_date": "2026-03-17T00:00:00", "home_or_away": "HOME", "min": 41.0, "pts": 18.5, "reb": 13.2, "ast": 3.5, "stl": 3.5, "blk": 1.7, "tov": 1.7, "fg3m": 3.5, "fga": 15.8, "fgm": 10.5, "fantasy_points": 49.5}, {"player_id": "20002003", "game_id": "23438", "team": "CHA", "opponent": "SA", "game_date": "2026-03-14T00:00:00", "home_or_away": "AWAY", "min": 44.0, "pts": 29.0, "reb": 7.0, "ast": 3.5, "stl": 1.7, "blk": 0.0, "tov": 3.5, "fg3m": 7.0, "fga": 21.1, "fgm": 10.6, "fantasy_points": 43.6}]}